{"Actuators": {"llSetTimerEvents": [{"wait_time": {"default": 5.0, "type": "float"}}], "state": [{"name": {"default": "default", "type": "string"}}], "llOwnerSay": [{"msg": {"default": "foo", "type": "string"}}], "llDie": [], "llListen": [{"channel": {"default": 0, "type": "int"}}, {"name": {"default": "", "type": "string"}}, {"id": {"default": "", "type": "key"}}, {"msg": {"default": "", "type": "string"}}], "llSay": [{"channel": {"default": 0, "type": "integer"}}, {"msg": {"default": "foo", "type": "string"}}], "llWhisper": "llSay"}, "Sensors": {"collision_end": "touch", "touch_end": "touch", "touch_start": "touch", "collision_start": "touch", "timer": [], "collision": "touch", "state_exit": [], "on_rez": [{"start_param": {"type": "integer"}}], "touch": [{"num_detected": {"type": "integer"}}], "state_entry": [], "listen": [{"channel": {"type": "integer"}}, {"name": {"type": "string"}}, {"id": {"type": "key"}}, {"message": {"type": "string"}}]}}